github/__init__.py
github/com/__init__.py
github/com/gogo/__init__.py
github/com/gogo/protobuf/__init__.py
github/com/gogo/protobuf/gogoproto/__init__.py
github/com/gogo/protobuf/gogoproto/gogo_pb2.py
gogo_python-0.0.1.dist-info/LICENSE
gogo_python-0.0.1.dist-info/METADATA
gogo_python-0.0.1.dist-info/WHEEL
gogo_python-0.0.1.dist-info/top_level.txt
gogo_python-0.0.1.dist-info/RECORD
